LICENSE
MANIFEST.in
README.md
setup.cfg
setup.py
ctrldaemon/__init__.py
ctrldaemon/ctrldaemon.py
ctrldaemon.egg-info/PKG-INFO
ctrldaemon.egg-info/SOURCES.txt
ctrldaemon.egg-info/dependency_links.txt
ctrldaemon.egg-info/not-zip-safe
ctrldaemon.egg-info/requires.txt
ctrldaemon.egg-info/top_level.txt