Metadata-Version: 1.1
Name: ctrldaemon
Version: 0.2
Summary: Service command wrapper for Python.
Home-page: http://www.yograterol.me
Author: Yohan Graterol
Author-email: yograterol@fedoraproject.org
License: BSD License
Download-URL: https://github.com/yograterol/python-ctrldaemon
Platform: UNKNOWN
